amapy_plugin_gcr/__init__.py
amapy_plugin_gcr/gcr_blob.py
amapy_plugin_gcr/gcr_mixin.py
amapy_plugin_gcr/gcr_storage.py
amapy_plugin_gcr/gcr_url.py
amapy_plugin_gcr/tests/__init__.py
amapy_plugin_gcr/tests/test_gcr_storage.py
amapy_plugin_gcr/tests/test_gcr_url.py
amapy_plugin_gcr/transporter/__init__.py
amapy_plugin_gcr/transporter/gcr_transporter.py
amapy_plugin_gcr-1.0.1.dist-info/METADATA
amapy_plugin_gcr-1.0.1.dist-info/WHEEL
amapy_plugin_gcr-1.0.1.dist-info/top_level.txt
amapy_plugin_gcr-1.0.1.dist-info/RECORD
